cisco_telescope/__init__.py
cisco_telescope/cmd/__init__.py
cisco_telescope/cmd/bootstrap.py
cisco_telescope/cmd/trace.py
cisco_telescope/configuration.py
cisco_telescope/consts.py
cisco_telescope/distro.py
cisco_telescope/exporter_factory.py
cisco_telescope/instrumentations/aiohttp/__init__.py
cisco_telescope/instrumentations/grpc/__init__.py
cisco_telescope/instrumentations/instrumentation_wrapper.py
cisco_telescope/instrumentations/pymongo/__init__.py
cisco_telescope/instrumentations/requests/__init__.py
cisco_telescope/instrumentations/utils.py
cisco_telescope/options.py
cisco_telescope/tracing.py
cisco_telescope-1.5.3.dist-info/entry_points.txt
cisco_telescope-1.5.3.dist-info/LICENSE
cisco_telescope-1.5.3.dist-info/WHEEL
cisco_telescope-1.5.3.dist-info/METADATA
cisco_telescope-1.5.3.dist-info/RECORD
