Metadata-Version: 2.1
Name: cisco-telescope
Version: 1.5.3
Summary: Cisco Distribution for OpenTelemetry
Home-page: https://github.com/cisco-open/otel-py
License: Apache-2.0
Author: Cisco Epsagon Team
Author-email: support@epsagon.com
Requires-Python: >=3.8,<4.0
Classifier: License :: OSI Approved :: Apache Software License
Classifier: Programming Language :: Python :: 3
Classifier: Programming Language :: Python :: 3.10
Classifier: Programming Language :: Python :: 3.8
Classifier: Programming Language :: Python :: 3.9
Requires-Dist: Flask (>=2.1.2,<3.0.0)
Requires-Dist: aiohttp (>=3.8.1,<4.0.0)
Requires-Dist: argparse (>=1.4.0,<2.0.0)
Requires-Dist: certifi (>=2022.5.18.1,<2023.0.0.0)
Requires-Dist: cisco-opentelemetry-specifications (>=0.0.21,<0.0.22)
Requires-Dist: fastapi (>=0.78.0,<0.79.0)
Requires-Dist: grpcio (>=1.46.3,<2.0.0)
Requires-Dist: httpcore (>=0.15.0,<0.16.0)
Requires-Dist: importlib-metadata (>=4.11.4,<5.0.0)
Requires-Dist: itsdangerous (>=2.1.2,<3.0.0)
Requires-Dist: opentelemetry-distro (>=0.29b)
Requires-Dist: opentelemetry-exporter-otlp (>=1.10.0)
Requires-Dist: opentelemetry-exporter-otlp-proto-grpc (>=1.10.0)
Requires-Dist: opentelemetry-exporter-otlp-proto-http (>=1.10.0)
Requires-Dist: opentelemetry-instrumentation-aiohttp-client (>=0.29b)
Requires-Dist: opentelemetry-instrumentation-fastapi (>=0.29b)
Requires-Dist: opentelemetry-instrumentation-flask (>=0.29b)
Requires-Dist: opentelemetry-instrumentation-grpc (>=0.29b)
Requires-Dist: opentelemetry-instrumentation-kafka-python (>=0.29b)
Requires-Dist: opentelemetry-instrumentation-pymongo (>=0.29b)
Requires-Dist: opentelemetry-instrumentation-requests (>=0.29b)
Requires-Dist: opentelemetry-sdk (>=1.10.0)
Requires-Dist: opentelemetry-util-http (>=0.29b)
Requires-Dist: packaging (>=21.3,<22.0)
Requires-Dist: protobuf (>=3.19.0,<4.0.0)
Requires-Dist: pymongo (>=3.12.3,<4.0.0)
Requires-Dist: requests (>=2.27.1,<3.0.0)
Requires-Dist: urllib3 (>=1.26.9,<2.0.0)
Requires-Dist: wheel (>=0.37.1,<0.38.0)
Project-URL: Repository, https://github.com/cisco-open/otel-py
